pyxet-0.1.10.dist-info/METADATA
pyxet-0.1.10.dist-info/WHEEL
pyxet-0.1.10.dist-info/entry_points.txt
pyxet/sync.py
pyxet/version.py
pyxet/rpyxet/__init__.py
pyxet/commit_transaction.py
pyxet/util.py
pyxet/file_interface.py
pyxet/__init__.py
pyxet/README.md
pyxet/url_parsing.py
pyxet/cli.py
pyxet/file_system.py
pyxet/pathlib.py
pyxet/file_operations.py
pyxet/rpyxet/rpyxet.abi3.so
pyxet-0.1.10.dist-info/RECORD
