Metadata-Version: 2.3
Name: pyxet
Version: 0.1.10
Classifier: Development Status :: 3 - Alpha
Classifier: Programming Language :: Rust
Classifier: Programming Language :: Python :: Implementation :: CPython
Classifier: Programming Language :: Python :: Implementation :: PyPy
Classifier: Programming Language :: Python
Classifier: Programming Language :: Python :: 3
Classifier: Programming Language :: Python :: 3 :: Only
Classifier: Programming Language :: Python :: 3.7
Classifier: Programming Language :: Python :: 3.8
Classifier: Programming Language :: Python :: 3.9
Classifier: Programming Language :: Python :: 3.10
Classifier: Programming Language :: Python :: 3.11
Classifier: Operating System :: POSIX :: Linux
Classifier: Operating System :: MacOS
Classifier: Topic :: Software Development :: Libraries :: Python Modules
Classifier: Topic :: System :: Filesystems
Classifier: Topic :: Software Development :: Version Control :: Git
Classifier: Topic :: Scientific/Engineering :: Artificial Intelligence
Requires-Dist: fsspec ==2023.9.2
Requires-Dist: typer >=0.9.0
Requires-Dist: tabulate >=0.9.0
Requires-Dist: s3fs >=2023.6.0
Summary: pyxet is a Python library that provides a lightweight interface for the XetHub platform.
Keywords: ai,collaboration,data-science,developer-tools,git,s3,machine-learning,reproducibility
Maintainer-email: XetHub <contact@xethub.com>
License: BSD-3-Clause
Requires-Python: >=3.7
Project-URL: Homepage, https://github.com/xetdata/pyxet
